{
  "entry": "c4889a3b-e226-49df-8007-f2fd08380c4d",
  "rule_sets": [
    {
      "uuid": "5e17178e-524b-4d82-8602-6c976bb430b0",
      "webhook_action": null,
      "rules": [
        {
          "test": {
            "test": "Yes Yep Y Ya",
            "type": "contains_any"
          },
          "category": "Yes",
          "destination": "e22137f0-873e-407f-89fd-c5ac47dad682",
          "uuid": "69bfd395-1d95-4046-9a7a-191cde7ea6c8",
          "destination_type": "A"
        },
        {
          "test": {
            "test": "No Nope N Nay",
            "type": "contains_any"
          },
          "category": "No",
          "destination": "68ada584-a80b-471a-9496-79c271466176",
          "uuid": "dde99c74-a3a2-44db-af94-94aa53b4e9d1",
          "destination_type": "A"
        },
        {
          "test": {
            "test": "true",
            "type": "true"
          },
          "category": "Other",
          "destination": "c0b99f60-2dba-480f-bc9e-c239684824c2",
          "uuid": "67392c7c-77d0-4050-8e17-a9ffbcc0d59d",
          "destination_type": "A"
        }
      ],
      "webhook": null,
      "ruleset_type": "wait_message",
      "label": "Filter Working",
      "operand": "@step.value",
      "finished_key": null,
      "response_type": "C",
      "y": 169,
      "x": 407
    }
  ],
  "action_sets": [
    {
      "y": 0,
      "x": 469,
      "destination": "5e17178e-524b-4d82-8602-6c976bb430b0",
      "uuid": "c4889a3b-e226-49df-8007-f2fd08380c4d",
      "actions": [
        {
          "msg": "Hi @contact.name, is your water filter working?  Answer with Yes or No.",
          "type": "reply"
        }
      ]
    },
    {
      "y": 43,
      "x": 783,
      "destination": "5e17178e-524b-4d82-8602-6c976bb430b0",
      "uuid": "c0b99f60-2dba-480f-bc9e-c239684824c2",
      "actions": [
        {
          "msg": "I'm sorry, I didn't understand that. Is your water filter still working?  Answer with Yes or No.",
          "type": "reply"
        }
      ]
    },
    {
      "y": 335,
      "x": 254,
      "destination": null,
      "uuid": "e22137f0-873e-407f-89fd-c5ac47dad682",
      "actions": [
        {
          "msg": "Great to hear, Thanks for your time!",
          "type": "reply"
        }
      ]
    },
    {
      "y": 346,
      "x": 543,
      "destination": null,
      "uuid": "68ada584-a80b-471a-9496-79c271466176",
      "actions": [
        {
          "msg": "Sorry to hear that, someone will be in touch to help you with your filter.",
          "type": "reply"
        }
      ]
    }
  ],
  "last_saved": "2015-07-23T04:17:05.382269Z",
  "metadata": {
    "notes": [
      {
        "body": "This single question poll demonstrates how TextIt can easily help measure what is happening in the field.",
        "x": 93,
        "y": 59,
        "title": "Simple Poll"
      }
    ]
  }
}
